pydnp3.cp38-win_amd64.pyd
pyopendnp3-0.1.0.dist-info/LICENSE
pyopendnp3-0.1.0.dist-info/METADATA
pyopendnp3-0.1.0.dist-info/WHEEL
pyopendnp3-0.1.0.dist-info/top_level.txt
pyopendnp3-0.1.0.dist-info/RECORD
