Metadata-Version: 2.1
Name: pyopendnp3
Version: 0.1.0
Summary: pyopendnp3 -- python binding for opendnp3
Home-page: https://github.com/garretfick/pydnp3
License: UNKNOWN
Platform: UNKNOWN
Requires-Dist: pybind11 (>=2.2)
Provides-Extra: dev
Requires-Dist: check-manifest ; extra == 'dev'
